{
  "object": "list",
  "results": [
    {
      "object": "block",
      "id": "26cd8e4e-98ab-8174-9758-ed9124b7eef0",
      "parent": {
        "type": "block_id",
        "block_id": "26cd8e4e-98ab-8035-a5b4-ea240d930619"
      },
      "created_time": "2025-09-12T06:32:00.000Z",
      "last_edited_time": "2025-09-12T06:32:00.000Z",
      "created_by": {
        "object": "user",
        "id": "019a87c7-d197-44a4-b19a-baa684400f81"
      },
      "last_edited_by": {
        "object": "user",
        "id": "019a87c7-d197-44a4-b19a-baa684400f81"
      },
      "has_children": false,
      "archived": false,
      "in_trash": false,
      "type": "bookmark",
      "bookmark": {
        "caption": [
          {
            "type": "text",
            "text": {
              "content": "Google",
              "link": null
            },
            "annotations": {
              "bold": false,
              "italic": false,
              "strikethrough": false,
              "underline": false,
              "code": false,
              "color": "default"
            },
            "plain_text": "Google",
            "href": null
          }
        ],
        "url": "https://www.google.com"
      }
    }
  ],
  "next_cursor": null,
  "has_more": false,
  "type": "block",
  "block": {},
  "request_id": "6c9cce7c-3ed0-4aa5-b87a-037e7fd18c34"
}
